torch_compose/__init__.py
torch_compose/demo.ipynb
torch_compose/module.py
torch_compose-0.2.0.dist-info/LICENSE
torch_compose-0.2.0.dist-info/METADATA
torch_compose-0.2.0.dist-info/WHEEL
torch_compose-0.2.0.dist-info/RECORD
